pommesdispatch/__init__.py
pommesdispatch/__main__.py
pommesdispatch/cli.py
pommesdispatch/model/__init__.py
pommesdispatch/model/dispatch_model.py
pommesdispatch/model_funcs/__init__.py
pommesdispatch/model_funcs/data_input.py
pommesdispatch/model_funcs/helpers.py
pommesdispatch/model_funcs/model_control.py
pommesdispatch/model_funcs/subroutines.py
pommesdispatch-0.1.0.dist-info/entry_points.txt
pommesdispatch-0.1.0.dist-info/LICENSE.md
pommesdispatch-0.1.0.dist-info/WHEEL
pommesdispatch-0.1.0.dist-info/METADATA
pommesdispatch-0.1.0.dist-info/RECORD
