Metadata-Version: 2.1
Name: pommesdispatch
Version: 0.1.0
Summary: A bottom-up fundamental power market model for the German electricity sector
Home-page: https://github.com/pommes-public/pommesdispatch/
License: MIT
Keywords: power market,fundamental model,dispatch,power price,oemof.solph
Author: Johannes Kochems
Author-email: jokochems@web.de
Maintainer: Johannes Kochems
Maintainer-email: jokochems@web.de
Requires-Python: >=3.8,<4.0
Classifier: Development Status :: 5 - Production/Stable
Classifier: License :: OSI Approved :: MIT License
Classifier: Programming Language :: Python :: 3
Classifier: Programming Language :: Python :: 3.8
Classifier: Programming Language :: Python :: 3.9
Provides-Extra: dev
Requires-Dist: numpy
Requires-Dist: oemof.solph (==0.4.4)
Requires-Dist: pandas
Requires-Dist: pyyaml
Project-URL: Changelog, https://pommesdispatch.readthedocs.io/en/latest/changelog.html
Project-URL: Documentation, https://pommesdispatch.readthedocs.io/
Project-URL: Issue Tracker, https://github.com/pommes-public/pommesdispatch/issues
Project-URL: Repository, https://github.com/pommes-public/pommesdispatch/
